MANIFEST.in
README.md
setup.py
tetest_python/__init__.py
tetest_python/te_config.json
tetest_python/te_constant.json
tetest_python/te_login.py
tetest_python/te_pytest_config.py
tetest_python/te_services.py
tetest_python.egg-info/PKG-INFO
tetest_python.egg-info/SOURCES.txt
tetest_python.egg-info/dependency_links.txt
tetest_python.egg-info/requires.txt
tetest_python.egg-info/top_level.txt
tetest_python.egg-info/zip-safe