Metadata-Version: 1.0
Name: tetest-python
Version: 1.1.1
Summary: Python Framework.
Home-page: UNKNOWN
Author: lu, chen-zhi
Author-email: UNKNOWN
License: ISC
Keywords: tetest python
Platform: any
